FLOPS_modern_interface/__init__.py
FLOPS_modern_interface/apirunner.py
FLOPS_modern_interface/input.py
FLOPS_modern_interface/output.py
FLOPS_modern_interface/runner.py
flops_modern_interface-0.0.2.dist-info/METADATA
flops_modern_interface-0.0.2.dist-info/WHEEL
flops_modern_interface-0.0.2.dist-info/licenses/LICENSE
flops_modern_interface-0.0.2.dist-info/RECORD
