Metadata-Version: 2.3
Name: FLOPS_modern_interface
Version: 0.0.2
Summary: Python pydantic classes for FLOPS input/output and web service
Project-URL: Homepage, https://cranfield-university-aedg.github.io/Pages/
Author-email: Sergio Jimeno <s.jimeno@cranfield.ac.uk>
License-File: LICENSE
Classifier: License :: OSI Approved :: MIT License
Classifier: Operating System :: OS Independent
Classifier: Programming Language :: Python :: 3
Requires-Python: >=3.11.9
Requires-Dist: pydantic>=2.7.4
Requires-Dist: requests>=2.32
